phas/__init__.py
phas/admin.py
phas/auth.py
phas/common.py
phas/db.py
phas/default_settings.py
phas/delegate.py
phas/dltrain.py
phas/dzi.py
phas/gcs_handler.py
phas/project_cli.py
phas/project_ref.py
phas/slide.py
phas/slideref.py
phas/client/__init__.py
phas/client/api.py
phas-0.98.9.dist-info/licenses/LICENSE.txt
phas-0.98.9.dist-info/METADATA
phas-0.98.9.dist-info/WHEEL
phas-0.98.9.dist-info/top_level.txt
phas-0.98.9.dist-info/RECORD
